explibrosa/__init__.py
explibrosa-0.0.0.dev1.dist-info/LICENSE
explibrosa-0.0.0.dev1.dist-info/METADATA
explibrosa-0.0.0.dev1.dist-info/WHEEL
explibrosa-0.0.0.dev1.dist-info/top_level.txt
explibrosa-0.0.0.dev1.dist-info/zip-safe
explibrosa-0.0.0.dev1.dist-info/RECORD
